rfbzero/__init__.py
rfbzero/crossover.py
rfbzero/degradation.py
rfbzero/experiment.py
rfbzero/py.typed
rfbzero/redox_flow_cell.py
rfbzero-1.0.1.dist-info/METADATA
rfbzero-1.0.1.dist-info/WHEEL
rfbzero-1.0.1.dist-info/licenses/AUTHORS
rfbzero-1.0.1.dist-info/licenses/LICENSE
rfbzero-1.0.1.dist-info/RECORD
