Metadata-Version: 2.3
Name: rfbzero
Version: 1.0.1
Summary: A package for zero dimensional simulation of electrochemical cycling in redox flow batteries
Project-URL: Homepage, https://github.com/ericfell/rfbzero
Project-URL: Documentation, https://rfbzero.readthedocs.io/en/latest/index.html#
Author-email: Eric Fell <efell@g.harvard.edu>, Jeremy Fell <jfell@sfu.ca>, Michael Aziz <maziz@harvard.edu>
License-File: AUTHORS
License-File: LICENSE
Keywords: batteries,electrochemistry,redox flow
Classifier: License :: OSI Approved :: MIT License
Classifier: Operating System :: OS Independent
Classifier: Programming Language :: Python :: 3
Requires-Python: >=3.10
Requires-Dist: scipy
